nonebot_plugin_emlp_Lightweight/Info.py
nonebot_plugin_emlp_Lightweight/__init__.py
nonebot_plugin_emlp_Lightweight/data/game/留档.TXT
nonebot_plugin_emlp_Lightweight/data/user/留档.TXT
nonebot_plugin_emlp_Lightweight/else_action.py
nonebot_plugin_emlp_Lightweight/emlp_rule.py
nonebot_plugin_emlp_Lightweight/props.py
nonebot_plugin_emlp_Lightweight/round_action.py
nonebot_plugin_emlp_Lightweight/user_action.py
nonebot_plugin_emlp_Lightweight/user_info.py
nonebot_plugin_emlp_lightweight-0.1.4.dist-info/METADATA
nonebot_plugin_emlp_lightweight-0.1.4.dist-info/WHEEL
nonebot_plugin_emlp_lightweight-0.1.4.dist-info/entry_points.txt
nonebot_plugin_emlp_lightweight-0.1.4.dist-info/RECORD
