Metadata-Version: 2.1
Name: nonebot_plugin_emlp_Lightweight
Version: 0.1.4
Summary: 轻量级恶魔轮盘插件
Author-Email: STESmly <3549337307@qq.com>
License: MIT
Project-URL: Homepage, https://github.com/STESmly/nonebot_plugin_emlp_Lightweight
Requires-Python: >=3.9
Requires-Dist: nonebot2>=2.4.1
Requires-Dist: nonebot-plugin-localstore>=0.7.3
